MANIFEST.in
setup.py
pybasicbayes/__init__.py
pybasicbayes/abstractions.py
pybasicbayes.egg-info/PKG-INFO
pybasicbayes.egg-info/SOURCES.txt
pybasicbayes.egg-info/dependency_links.txt
pybasicbayes.egg-info/requires.txt
pybasicbayes.egg-info/top_level.txt
pybasicbayes/distributions/__init__.py
pybasicbayes/distributions/binomial.py
pybasicbayes/distributions/gaussian.py
pybasicbayes/distributions/geometric.py
pybasicbayes/distributions/meta.py
pybasicbayes/distributions/multinomial.py
pybasicbayes/distributions/negativebinomial.py
pybasicbayes/distributions/poisson.py
pybasicbayes/distributions/regression.py
pybasicbayes/distributions/uniform.py
pybasicbayes/models/__init__.py
pybasicbayes/models/factor_analysis.py
pybasicbayes/models/mixture.py
pybasicbayes/models/parallel_mixture.py
pybasicbayes/testing/__init__.py
pybasicbayes/testing/mixins.py
pybasicbayes/util/__init__.py
pybasicbayes/util/cstats.c
pybasicbayes/util/cstats.pyx
pybasicbayes/util/cyutil.py
pybasicbayes/util/general.py
pybasicbayes/util/plot.py
pybasicbayes/util/profiling.py
pybasicbayes/util/stats.py
pybasicbayes/util/testing.py
pybasicbayes/util/text.py